{
    "overall": {
        "default": {
            "label": "CondCondChecker",
            "num_samples": 11,
            "num_violations": 9,
            "avg_violation": 0.068394,
            "avg_violation_no_outliers": 0.064008,
            "median_violation": 0.050366
        },
        "frequentist": {
            "label": "CondCondChecker",
            "num_samples": 11,
            "num_violations": 10,
            "avg_violation": 0.366965,
            "avg_violation_no_outliers": 0.367004,
            "median_violation": 0.317874
        }
    },
    "by_source": {
        "Will Ukraine join NATO before 2030?": {
            "default": {
                "label": "CondCondChecker_Will Ukraine join NATO before 2030?",
                "num_samples": 4,
                "num_violations": 3,
                "avg_violation": 0.067031,
                "avg_violation_no_outliers": 0.045931,
                "median_violation": 0.045931
            },
            "frequentist": {
                "label": "CondCondChecker_Will Ukraine join NATO before 2030?",
                "num_samples": 4,
                "num_violations": 4,
                "avg_violation": 0.399439,
                "avg_violation_no_outliers": 0.361873,
                "median_violation": 0.361873
            },
            "source_id": "11606184-0da5-4438-a9ff-123363119bea"
        },
        "Will a new infectious disease prompt the development of nuclear biocontainment technologies before 2030?": {
            "default": {
                "label": "CondCondChecker_Will a new infectious disease prompt the development of nuclear biocontainment technologies before 2030?",
                "num_samples": 4,
                "num_violations": 3,
                "avg_violation": 0.059139,
                "avg_violation_no_outliers": 0.049389,
                "median_violation": 0.049389
            },
            "frequentist": {
                "label": "CondCondChecker_Will a new infectious disease prompt the development of nuclear biocontainment technologies before 2030?",
                "num_samples": 4,
                "num_violations": 3,
                "avg_violation": 0.319734,
                "avg_violation_no_outliers": 0.343961,
                "median_violation": 0.343961
            },
            "source_id": "555cabf3-b51d-4a1a-9ebb-f6817b0b38d6"
        },
        "Will a Formula 1 Grand Prix be hosted in a country currently under international sanctions by 2025?": {
            "default": {
                "label": "CondCondChecker_Will a Formula 1 Grand Prix be hosted in a country currently under international sanctions by 2025?",
                "num_samples": 3,
                "num_violations": 3,
                "avg_violation": 0.082552,
                "avg_violation_no_outliers": 0.050366,
                "median_violation": 0.050366
            },
            "frequentist": {
                "label": "CondCondChecker_Will a Formula 1 Grand Prix be hosted in a country currently under international sanctions by 2025?",
                "num_samples": 3,
                "num_violations": 3,
                "avg_violation": 0.386641,
                "avg_violation_no_outliers": 0.317874,
                "median_violation": 0.317874
            },
            "source_id": "ce5ae624-4697-44b8-9cf2-4ef3deee74ad"
        }
    }
}